odoo/addons/l10n_et_tz/README.rst
odoo/addons/l10n_et_tz/__init__.py
odoo/addons/l10n_et_tz/__manifest__.py
odoo/addons/l10n_et_tz/data/l10n_et_data.xml
odoo/addons/l10n_et_tz/models/__init__.py
odoo/addons/l10n_et_tz/models/res_partner.py
odoo/addons/l10n_et_tz/readme/CREDITS.rst
odoo/addons/l10n_et_tz/readme/DESCRIPTION.rst
odoo/addons/l10n_et_tz/static/description/icon.png
odoo/addons/l10n_et_tz/static/description/index.html
odoo/addons/l10n_et_tz/static/src/img/main_screenshot.png
odoo/addons/l10n_et_tz/tests/__init__.py
odoo/addons/l10n_et_tz/tests/test_res_users.py
odoo14_addon_l10n_et_tz-14.0.1.0.1.dev5.dist-info/METADATA
odoo14_addon_l10n_et_tz-14.0.1.0.1.dev5.dist-info/WHEEL
odoo14_addon_l10n_et_tz-14.0.1.0.1.dev5.dist-info/top_level.txt
odoo14_addon_l10n_et_tz-14.0.1.0.1.dev5.dist-info/RECORD
